{
  "pair": "ETH",
  "mode": "pro",
  "amountPerTrade": 0.001,
  "intervalMinutes": 30,
  "maxSlippage": 1.5,
  "stopLoss": null,
  "takeProfit": null,
  "stopLossPercent": 3,
  "takeProfitPercent": 5,
  "rsiPeriod": 14,
  "rsiOversold": 35,
  "rsiOverbought": 65,
  "tradePercent": 1,
  "checkIntervalSeconds": 45,
  "candleInterval": "15m",
  "timeframes": {
    "macro": "4h",
    "trend": "1h",
    "entry": "15m"
  },
  "riskPerTradePercent": 0.5,
  "maxPositionPercent": 20,
  "maxDailyLossPercent": 2,
  "maxDrawdownPercent": 8,
  "consecutiveLossLimit": 3,
  "lossCooldownMinutes": 240,
  "minConfidenceScore": 70,
  "atrStopMultiplier": 2,
  "atrTrailMultiplier": 1,
  "atrTp1Multiplier": 2,
  "atrTp2Multiplier": 3,
  "partialTakeProfitPercent": 50,
  "scaleInEnabled": true,
  "maxFundingRate": 0.00005,
  "minVolumeRatio": 1.1,
  "watchlist": [
    "ETH",
    "BTC",
    "SOL"
  ],
  "scannerEnabled": false,
  "aiSignalEnabled": false,
  "active": false,
  "lastTradeAt": null,
  "lastSignal": null,
  "lastDecision": null,
  "trailingPeak": null,
  "tp1Taken": false,
  "scaleInPending": false,
  "positionLeg": null,
  "createdAt": "2026-07-16T13:54:36.868Z",
  "updatedAt": "2026-07-16T13:54:36.869Z",
  "aiDynamicThreshold": false,
  "aiExitEnabled": false,
  "aiTakeProfitEnabled": false,
  "_comment": "Copia come strategy.json (in DATA_DIR / root). active=false di default: attiva da Telegram o API dopo verifica demo."
}